tests/__init__.py
tests/test_config.py
tests/test_logging.py
yirgachefe/__init__.py
yirgachefe/config_.py
yirgachefe/logger_.py
yirgachefe/logger_.pyi
yirgachefe-0.1.6.dist-info/LICENSE
yirgachefe-0.1.6.dist-info/METADATA
yirgachefe-0.1.6.dist-info/WHEEL
yirgachefe-0.1.6.dist-info/top_level.txt
yirgachefe-0.1.6.dist-info/RECORD
