Metadata-Version: 2.1
Name: yirgachefe
Version: 0.1.6
Summary: Convenience of configuration and logging.
Home-page: https://github.com/iconloop/Yirgachefe
Author: ICONLOOP
Author-email: t_core@iconloop.com
Requires-Python: >=3.7.5
License-File: LICENSE
Requires-Dist: coloredlogs (~=15.0.0)
Provides-Extra: dev
Requires-Dist: pytest ; extra == 'dev'
Requires-Dist: flake8 ; extra == 'dev'
Requires-Dist: flake8-docstrings ; extra == 'dev'
Provides-Extra: lint
Requires-Dist: flake8 ; extra == 'lint'
Requires-Dist: flake8-docstrings ; extra == 'lint'
Provides-Extra: tests
Requires-Dist: pytest ; extra == 'tests'
